AUTHORS
CONTRIBUTING.rst
ChangeLog
HACKING.rst
LICENSE
MANIFEST.in
README.rst
requirements.txt
setup.cfg
setup.py
test-requirements.txt
tox.ini
networking_generic_switch_tempest_plugin.egg-info/PKG-INFO
networking_generic_switch_tempest_plugin.egg-info/SOURCES.txt
networking_generic_switch_tempest_plugin.egg-info/dependency_links.txt
networking_generic_switch_tempest_plugin.egg-info/entry_points.txt
networking_generic_switch_tempest_plugin.egg-info/not-zip-safe
networking_generic_switch_tempest_plugin.egg-info/pbr.json
networking_generic_switch_tempest_plugin.egg-info/requires.txt
networking_generic_switch_tempest_plugin.egg-info/top_level.txt
tempest_plugin/README.rst
tempest_plugin/__init__.py
tempest_plugin/config.py
tempest_plugin/plugin.py
tempest_plugin/tests/__init__.py
tempest_plugin/tests/common/__init__.py
tempest_plugin/tests/common/ovs_lib.py
tempest_plugin/tests/scenario/__init__.py
tempest_plugin/tests/scenario/test_ngs_basic_ops.py